{"body":"This is a simple Javascript library to upload a file to Amazon S3 asynchronously.\r\n\r\n## Usage\r\n\r\n### Markup\r\n\r\n    <html>\r\n      <head>\r\n        <script type='text/javascript' src='s3uploader.js'></script>\r\n      <head>\r\n      <body>\r\n        <input type='hidden' id='bucket' value='YourBucket'>\r\n        <input type='hidden' id='key' value='AKey'>\r\n        <input type='hidden' id='acl' value='YourACL'>\r\n        <input type='hidden' id='AWSAccessKeyId' value='YourAWSAccessKeyId'>\r\n        <input type='hidden' id='policy' value='Base64Encodedpolicy'>\r\n        <input type='hidden' id='signature' value='Base64EncodedSignature'>\r\n        <input name=\"template\" type=\"file\">\r\n        <button id='submit'>Upload</button>\r\n      </body>\r\n    </html>\r\n\r\n### Javascript\r\n\r\n    file = document.getElementById('submit').files[0];\r\n    uploader = new S3Uploader();\r\n    uploader.onStart = myStartCallback;\r\n    uploader.onProgress = myProgressCallback; // passes the completion fraction as argument\r\n    uploader.onComplete = myCompleteCallback;\r\n    uploader.onError = myErrorCallback;\r\n    uploader.upload(file);\r\n\r\n## Support\r\n\r\nTweet me up at [@neutralino1](http://twitter.com/neutralino1) for questions and requests.","tagline":"An Amazon S3 Ajax uploader","google":"","note":"Don't delete this file! It's used internally to help with page regeneration.","name":"s3uploader.js"}